django_ask_sdk/__init__.py
django_ask_sdk/__version__.py
django_ask_sdk/skill_adapter.py
django_ask_sdk-1.0.0.dist-info/METADATA
django_ask_sdk-1.0.0.dist-info/RECORD
django_ask_sdk-1.0.0.dist-info/WHEEL
django_ask_sdk-1.0.0.dist-info/top_level.txt
